memcache_toolbar
