Metadata-Version: 1.1
Name: memcache-toolbar
Version: 0.5.6
Summary: Add-on for Django Debug Toolbar for tracking memcached usage
Home-page: http://github.com/ross/memcache-debug-panel
Author: Ross McFarland
Author-email: rwmcfa1@neces.com
License: UNKNOWN
Platform: UNKNOWN
Requires: Django
Requires: debug_toolbar
Provides: memcache_toolbar
